scscp/__init__.py
scscp/cli.py
scscp/client.py
scscp/processing_instruction.py
scscp/scscp.py
scscp/server.py
scscp-0.1.1.dist-info/DESCRIPTION.rst
scscp-0.1.1.dist-info/METADATA
scscp-0.1.1.dist-info/RECORD
scscp-0.1.1.dist-info/WHEEL
scscp-0.1.1.dist-info/metadata.json
scscp-0.1.1.dist-info/top_level.txt
