Metadata-Version: 2.0
Name: scscp
Version: 0.1.1
Summary: Implementation of the SCSCP protocol
Home-page: https://github.com/OpenMath/py-scscp
Author: Luca De Feo
Author-email: UNKNOWN
License: MIT
Keywords: openmath scscp
Platform: UNKNOWN
Classifier: Intended Audience :: Science/Research
Classifier: License :: OSI Approved :: MIT License
Classifier: Programming Language :: Python :: 2
Classifier: Programming Language :: Python :: 3
Requires-Dist: openmath (>=0.1.1)
Requires-Dist: pexpect
